.gitignore
README.md
setup.py
bin/fetch-ticket
bin/force-build
bin/get-attachment
bin/mkbranch
bin/review-tickets
twisted_dev_tools.egg-info/PKG-INFO
twisted_dev_tools.egg-info/SOURCES.txt
twisted_dev_tools.egg-info/dependency_links.txt
twisted_dev_tools.egg-info/not-zip-safe
twisted_dev_tools.egg-info/requires.txt
twisted_dev_tools.egg-info/top_level.txt
twisted_tools/__init__.py
twisted_tools/buildbot.py
twisted_tools/git.py
twisted_tools/scripts/__init__.py
twisted_tools/scripts/fetchticket.py
twisted_tools/scripts/forcebuild.py
twisted_tools/scripts/getattachment.py
twisted_tools/scripts/reviewtickets.py
twisted_tools/test/__init__.py
twisted_tools/test/test_git.py