Metadata-Version: 1.0
Name: twisted-dev-tools
Version: 0.0.2
Summary: Tools for twisted development
Home-page: https://github.com/twisted/twisted-dev-tools
Author: Tom Prince
Author-email: tom.prince@twistedmatrix.com
License: MIT
Platform: UNKNOWN
